CHANGELOG.txt
LICENSE
MANIFEST.in
README.txt
setup.py
core/battery_info.py
core/cpu_info.py
core/device_info.py
core/display_info.py
core/exception.py
core/gpu_info.py
core/machine_info.py
core/motherboard_info.py
core/network_info.py
core/ram_info.py
core/sound_info.py
core/storage_info.py
core/system_info.py
pysil/__init__.py
pysil.egg-info/PKG-INFO
pysil.egg-info/SOURCES.txt
pysil.egg-info/dependency_links.txt
pysil.egg-info/requires.txt
pysil.egg-info/top_level.txt
pysil_demo/gui.py
venv/Lib/site-packages/_sounddevice.py
venv/Lib/site-packages/_virtualenv.py
venv/Lib/site-packages/pythoncom.py
venv/Lib/site-packages/pywin32.version.txt
venv/Lib/site-packages/sounddevice.py
venv/Lib/site-packages/speedtest.py
venv/Lib/site-packages/speedtest_cli.py
venv/Lib/site-packages/typing.py
venv/Lib/site-packages/wmi.py
venv/Lib/site-packages/GPUtil/GPUtil.py
venv/Lib/site-packages/GPUtil/__init__.py
venv/Lib/site-packages/GPUtil/demo_GPUtil.py
venv/Lib/site-packages/GPUtil-1.4.0.dist-info/top_level.txt
venv/Lib/site-packages/WMI-1.5.1.dist-info/top_level.txt
venv/Lib/site-packages/_distutils_hack/__init__.py
venv/Lib/site-packages/_distutils_hack/override.py
venv/Lib/site-packages/_sounddevice_data/__init__.py
venv/Lib/site-packages/adodbapi/__init__.py
venv/Lib/site-packages/adodbapi/ado_consts.py
venv/Lib/site-packages/adodbapi/adodbapi.py
venv/Lib/site-packages/adodbapi/apibase.py
venv/Lib/site-packages/adodbapi/is64bit.py
venv/Lib/site-packages/adodbapi/license.txt
venv/Lib/site-packages/adodbapi/process_connect_string.py
venv/Lib/site-packages/adodbapi/readme.txt
venv/Lib/site-packages/adodbapi/remote.py
venv/Lib/site-packages/adodbapi/schema_table.py
venv/Lib/site-packages/adodbapi/setup.py
venv/Lib/site-packages/adodbapi/examples/db_print.py
venv/Lib/site-packages/adodbapi/examples/db_table_names.py
venv/Lib/site-packages/adodbapi/examples/xls_read.py
venv/Lib/site-packages/adodbapi/examples/xls_write.py
venv/Lib/site-packages/adodbapi/test/adodbapitest.py
venv/Lib/site-packages/adodbapi/test/adodbapitestconfig.py
venv/Lib/site-packages/adodbapi/test/dbapi20.py
venv/Lib/site-packages/adodbapi/test/is64bit.py
venv/Lib/site-packages/adodbapi/test/setuptestframework.py
venv/Lib/site-packages/certifi-2021.10.8.dist-info/top_level.txt
venv/Lib/site-packages/cffi-1.15.0.dist-info/entry_points.txt
venv/Lib/site-packages/cffi-1.15.0.dist-info/top_level.txt
venv/Lib/site-packages/charset_normalizer-2.0.12.dist-info/entry_points.txt
venv/Lib/site-packages/charset_normalizer-2.0.12.dist-info/top_level.txt
venv/Lib/site-packages/clr-1.0.3.dist-info/top_level.txt
venv/Lib/site-packages/colorzero-2.0.dist-info/LICENSE.txt
venv/Lib/site-packages/colorzero-2.0.dist-info/top_level.txt
venv/Lib/site-packages/distro-1.7.0.dist-info/entry_points.txt
venv/Lib/site-packages/distro-1.7.0.dist-info/top_level.txt
venv/Lib/site-packages/gpiozero-1.6.2.dist-info/entry_points.txt
venv/Lib/site-packages/gpiozero-1.6.2.dist-info/top_level.txt
venv/Lib/site-packages/idna-3.3.dist-info/top_level.txt
venv/Lib/site-packages/netifaces-0.11.0.dist-info/top_level.txt
venv/Lib/site-packages/pip-21.1.2.dist-info/LICENSE.txt
venv/Lib/site-packages/pip-21.1.2.dist-info/entry_points.txt
venv/Lib/site-packages/pip-21.1.2.dist-info/top_level.txt
venv/Lib/site-packages/psutil-5.9.0.dist-info/top_level.txt
venv/Lib/site-packages/py_cpuinfo-8.0.0.dist-info/entry_points.txt
venv/Lib/site-packages/py_cpuinfo-8.0.0.dist-info/top_level.txt
venv/Lib/site-packages/pycparser-2.21.dist-info/top_level.txt
venv/Lib/site-packages/pyedid-1.0.1.dist-info/top_level.txt
venv/Lib/site-packages/pywin32-304.dist-info/top_level.txt
venv/Lib/site-packages/requests-2.27.1.dist-info/top_level.txt
venv/Lib/site-packages/setuptools-57.4.0.dist-info/entry_points.txt
venv/Lib/site-packages/setuptools-57.4.0.dist-info/top_level.txt
venv/Lib/site-packages/sounddevice-0.4.4.dist-info/top_level.txt
venv/Lib/site-packages/speedtest_cli-2.1.3.dist-info/entry_points.txt
venv/Lib/site-packages/speedtest_cli-2.1.3.dist-info/top_level.txt
venv/Lib/site-packages/typing-3.7.4.3.dist-info/top_level.txt
venv/Lib/site-packages/urllib3-1.26.9.dist-info/LICENSE.txt
venv/Lib/site-packages/urllib3-1.26.9.dist-info/top_level.txt
venv/Lib/site-packages/wheel-0.36.2.dist-info/LICENSE.txt
venv/Lib/site-packages/wheel-0.36.2.dist-info/entry_points.txt
venv/Lib/site-packages/wheel-0.36.2.dist-info/top_level.txt
venv/Lib/site-packages/windows_tools.antivirus-0.7.2.dist-info/namespace_packages.txt
venv/Lib/site-packages/windows_tools.antivirus-0.7.2.dist-info/top_level.txt
venv/Lib/site-packages/windows_tools.installed_software-0.5.4.dist-info/namespace_packages.txt
venv/Lib/site-packages/windows_tools.installed_software-0.5.4.dist-info/top_level.txt
venv/Lib/site-packages/windows_tools.misc-1.0.0.dist-info/namespace_packages.txt
venv/Lib/site-packages/windows_tools.misc-1.0.0.dist-info/top_level.txt
venv/Lib/site-packages/windows_tools.registry-1.0.1.dist-info/namespace_packages.txt
venv/Lib/site-packages/windows_tools.registry-1.0.1.dist-info/top_level.txt
venv/Lib/site-packages/windows_tools.wmi_queries-0.9.7.dist-info/namespace_packages.txt
venv/Lib/site-packages/windows_tools.wmi_queries-0.9.7.dist-info/top_level.txt
