Metadata-Version: 2.1
Name: pysil
Version: 1.1.5
Summary: system information gathering made simple
Home-page: https://github.com/Bamboooz/pysil
Author: Bamboooz
Author-email: bambusixmc@gmail.com
License: MIT
Keywords: system
Platform: UNKNOWN
Classifier: Development Status :: 5 - Production/Stable
Classifier: Operating System :: Microsoft :: Windows :: Windows 10
Classifier: Programming Language :: Python :: 3
License-File: LICENSE
